simple_select2/__init__.py
simple_select2/admin.py
simple_select2/filters.py
simple_select2/views.py
simple_select2/widgets.py
django_simple_select2-0.2.0.dist-info/LICENSE
django_simple_select2-0.2.0.dist-info/METADATA
django_simple_select2-0.2.0.dist-info/WHEEL
django_simple_select2-0.2.0.dist-info/top_level.txt
django_simple_select2-0.2.0.dist-info/RECORD
