Metadata-Version: 2.1
Name: django-simple-select2
Version: 0.2.0
Summary: Tweaks for existing built-in Django's autocomplete feature
Home-page: https://github.com/jerinpetergeorge/django-simple-select2
Author: Jerin Peter George
Author-email: jerinpetergeorge@gmail.com
License: MIT-Zero
Download-URL: https://github.com/jerinpetergeorge/django-simple-select2/archive/v0.2.0.tar.gz
Platform: UNKNOWN
Requires-Python: >=3.6
Requires-Dist: Django (>=2.2)
